asciitext/__init__.py
asciitext-0.0.5.dist-info/LICENSE
asciitext-0.0.5.dist-info/METADATA
asciitext-0.0.5.dist-info/WHEEL
asciitext-0.0.5.dist-info/top_level.txt
asciitext-0.0.5.dist-info/RECORD
