Metadata-Version: 2.1
Name: asciitext
Version: 0.0.5
Summary: Text to ASCII Art Generator.
Home-page: UNKNOWN
Author: YasserBDJ96
Author-email: yasser.bdj96@gmail.com
License: MIT License
Project-URL: Source Code, https://github.com/yasserbdj96/asciitext
Project-URL: Author WebSite, https://yasserbdj96.github.io/
Project-URL: Instagram, https://www.instagram.com/yasserbdj96/
Keywords: yasserbdj96,python,ascii,texts,colors.,hex,background,rgb
Platform: UNKNOWN
Classifier: Development Status :: 5 - Production/Stable
Classifier: Intended Audience :: Developers
Classifier: License :: OSI Approved :: MIT License
Classifier: Programming Language :: Python :: 3
Classifier: Operating System :: Unix
Classifier: Operating System :: MacOS :: MacOS X
Classifier: Operating System :: Microsoft :: Windows
Classifier: Topic :: Software Development :: Build Tools
Classifier: Topic :: Software Development :: Libraries :: Python Modules
Classifier: Topic :: Communications :: Email
Requires-Python: >=3.x.x
License-File: LICENSE
Requires-Dist: hexor
Requires-Dist: requests
